{"nodes": [{"id": "c_users_leonardo_reales_desktop_sigaf_frontend_web_src_hooks_useactivitylog_ts", "label": "useActivityLog.ts", "file_type": "code", "source_file": "C:\\Users\\Leonardo Reales\\Desktop\\SIGAF\\Frontend\\web\\src\\hooks\\useActivityLog.ts", "source_location": "L1"}, {"id": "hooks_useactivitylog_useactivitylog", "label": "useActivityLog()", "file_type": "code", "source_file": "C:\\Users\\Leonardo Reales\\Desktop\\SIGAF\\Frontend\\web\\src\\hooks\\useActivityLog.ts", "source_location": "L6"}], "edges": [{"source": "c_users_leonardo_reales_desktop_sigaf_frontend_web_src_hooks_useactivitylog_ts", "target": "react", "relation": "imports_from", "context": "import", "confidence": "EXTRACTED", "source_file": "C:\\Users\\Leonardo Reales\\Desktop\\SIGAF\\Frontend\\web\\src\\hooks\\useActivityLog.ts", "source_location": "L1", "weight": 1.0}, {"source": "c_users_leonardo_reales_desktop_sigaf_frontend_web_src_hooks_useactivitylog_ts", "target": "c_users_leonardo_reales_desktop_sigaf_frontend_web_src_lib_activitybus_ts", "relation": "imports_from", "context": "import", "confidence": "EXTRACTED", "source_file": "C:\\Users\\Leonardo Reales\\Desktop\\SIGAF\\Frontend\\web\\src\\hooks\\useActivityLog.ts", "source_location": "L2", "weight": 1.0}, {"source": "c_users_leonardo_reales_desktop_sigaf_frontend_web_src_hooks_useactivitylog_ts", "target": "lib_activitybus_activitybus", "relation": "imports", "context": "import", "confidence": "EXTRACTED", "source_file": "C:\\Users\\Leonardo Reales\\Desktop\\SIGAF\\Frontend\\web\\src\\hooks\\useActivityLog.ts", "source_location": "L2", "weight": 1.0}, {"source": "c_users_leonardo_reales_desktop_sigaf_frontend_web_src_hooks_useactivitylog_ts", "target": "lib_activitybus_loadactivitylog", "relation": "imports", "context": "import", "confidence": "EXTRACTED", "source_file": "C:\\Users\\Leonardo Reales\\Desktop\\SIGAF\\Frontend\\web\\src\\hooks\\useActivityLog.ts", "source_location": "L2", "weight": 1.0}, {"source": "c_users_leonardo_reales_desktop_sigaf_frontend_web_src_hooks_useactivitylog_ts", "target": "lib_activitybus_activityentry", "relation": "imports", "context": "import", "confidence": "EXTRACTED", "source_file": "C:\\Users\\Leonardo Reales\\Desktop\\SIGAF\\Frontend\\web\\src\\hooks\\useActivityLog.ts", "source_location": "L2", "weight": 1.0}, {"source": "c_users_leonardo_reales_desktop_sigaf_frontend_web_src_hooks_useactivitylog_ts", "target": "hooks_useactivitylog_useactivitylog", "relation": "contains", "confidence": "EXTRACTED", "source_file": "C:\\Users\\Leonardo Reales\\Desktop\\SIGAF\\Frontend\\web\\src\\hooks\\useActivityLog.ts", "source_location": "L6", "weight": 1.0}], "raw_calls": [{"caller_nid": "hooks_useactivitylog_useactivitylog", "callee": "useState", "is_member_call": false, "source_file": "C:\\Users\\Leonardo Reales\\Desktop\\SIGAF\\Frontend\\web\\src\\hooks\\useActivityLog.ts", "source_location": "L7"}, {"caller_nid": "hooks_useactivitylog_useactivitylog", "callee": "useEffect", "is_member_call": false, "source_file": "C:\\Users\\Leonardo Reales\\Desktop\\SIGAF\\Frontend\\web\\src\\hooks\\useActivityLog.ts", "source_location": "L9"}]}